ranking_table_tennis/__init__.py
ranking_table_tennis/command_line.py
ranking_table_tennis/compute_rankings.py
ranking_table_tennis/config/base_config/activeplayer.yaml
ranking_table_tennis/config/base_config/base_config.yaml
ranking_table_tennis/config/base_config/initial_metadata.yaml
ranking_table_tennis/config/base_config/labels.yaml
ranking_table_tennis/config/base_config/roundnames.yaml
ranking_table_tennis/config/base_config/sheetname.yaml
ranking_table_tennis/config/compute/base_compute.yaml
ranking_table_tennis/config/compute/compute_2021_1.yaml
ranking_table_tennis/config/compute/compute_2022_1.yaml
ranking_table_tennis/config/compute/compute_2022_2.yaml
ranking_table_tennis/config/compute/compute_2023_1.yaml
ranking_table_tennis/config/compute/compute_2024_1.yaml
ranking_table_tennis/config/compute/compute_2025_1.yaml
ranking_table_tennis/config/compute/compute_2025_2.yaml
ranking_table_tennis/config/config_210101_211231.yaml
ranking_table_tennis/config/config_220101_220723.yaml
ranking_table_tennis/config/config_220724_221231.yaml
ranking_table_tennis/config/config_230101_231231.yaml
ranking_table_tennis/config/config_240101_241231.yaml
ranking_table_tennis/config/config_250101_250531.yaml
ranking_table_tennis/config/config_250601_251231.yaml
ranking_table_tennis/config/expected_result.csv
ranking_table_tennis/config/io/base_io.yaml
ranking_table_tennis/config/io/io_2021.yaml
ranking_table_tennis/config/io/io_2022.yaml
ranking_table_tennis/config/io/io_2023.yaml
ranking_table_tennis/config/io/io_2024.yaml
ranking_table_tennis/config/io/io_2025.yaml
ranking_table_tennis/config/logging.yaml
ranking_table_tennis/config/points_per_round.csv
ranking_table_tennis/config/unexpected_result.csv
ranking_table_tennis/configs.py
ranking_table_tennis/helpers/__init__.py
ranking_table_tennis/helpers/excel.py
ranking_table_tennis/helpers/github.py
ranking_table_tennis/helpers/gspread.py
ranking_table_tennis/helpers/initial_rating.py
ranking_table_tennis-2025.9.24.dist-info/LICENSE
ranking_table_tennis-2025.9.24.dist-info/METADATA
ranking_table_tennis-2025.9.24.dist-info/WHEEL
ranking_table_tennis-2025.9.24.dist-info/entry_points.txt
ranking_table_tennis-2025.9.24.dist-info/RECORD
