Metadata-Version: 2.3
Name: ranking_table_tennis
Version: 2025.9.24
Summary: A ranking table tennis system
License: GPL-2.0-or-later
Author: Sebastian Vanrell srvanrell_gmail_com
Requires-Python: >=3.10,<4
Classifier: License :: OSI Approved :: GNU General Public License v2 or later (GPLv2+)
Classifier: License :: OSI Approved :: MIT License
Classifier: Operating System :: POSIX :: Linux
Classifier: Programming Language :: Python :: 3
Classifier: Programming Language :: Python :: 3.10
Classifier: Programming Language :: Python :: 3.11
Classifier: Programming Language :: Python :: 3.12
Classifier: Programming Language :: Python :: 3.13
Requires-Dist: PyYAML (>=5.4.1)
Requires-Dist: Unidecode (==1.*)
Requires-Dist: gspread (==5.*)
Requires-Dist: gspread-dataframe (==3.*)
Requires-Dist: hydra-core (==1.3.*)
Requires-Dist: matplotlib (==3.*)
Requires-Dist: numpy (>=1.24,<2)
Requires-Dist: oauth2client (==4.*)
Requires-Dist: omegaconf (==2.3.*)
Requires-Dist: openpyxl (==3.1.*)
Requires-Dist: pandas (==2.2.*)
Requires-Dist: plotly (==5.*)
Requires-Dist: tabulate (==0.9.*)
Requires-Dist: urllib3 (==2.*)
Project-URL: Homepage, https://srvanrell.github.io/ranking-table-tennis/
Project-URL: Repository, http://github.com/srvanrell/ranking-table-tennis
